{
  "project_info": {
    "project_number": "222201864333",
    "firebase_url": "https://proiect-android-livescore-default-rtdb.europe-west1.firebasedatabase.app",
    "project_id": "proiect-android-livescore",
    "storage_bucket": "proiect-android-livescore.appspot.com"
  },
  "client": [
    {
      "client_info": {
        "mobilesdk_app_id": "1:222201864333:android:08d962f8b65c9ad66682c4",
        "android_client_info": {
          "package_name": "ro.ase.proiectandroidlivescore"
        }
      },
      "oauth_client": [
        {
          "client_id": "222201864333-bjp5kpuq1rgs6c05t2j8ap2rc0a9nu21.apps.googleusercontent.com",
          "client_type": 3
        }
      ],
      "api_key": [
        {
          "current_key": "AIzaSyBD5c9mEGHf1qKXSKZdAOtkWvb8Sh5Ee8w"
        }
      ],
      "services": {
        "appinvite_service": {
          "other_platform_oauth_client": [
            {
              "client_id": "222201864333-bjp5kpuq1rgs6c05t2j8ap2rc0a9nu21.apps.googleusercontent.com",
              "client_type": 3
            }
          ]
        }
      }
    }
  ],
  "configuration_version": "1"
}